sentry_campfire
