Metadata-Version: 1.0
Name: sentry-campfire
Version: 0.1.1
Summary: A Sentry Campfire notification plugin
Home-page: https://github.com/mkhattab/sentry-campfire
Author: Mustafa Khattab
Author-email: mustafa.khattab@gmail.com
License: BSD
Keywords: sentry-campfire sentry campfire
Platform: UNKNOWN
Classifier: Framework :: Django
Classifier: Intended Audience :: Developers
Classifier: Intended Audience :: System Administrators
Classifier: Operating System :: OS Independent
Classifier: Topic :: Software Development
